{
  "update_time": "2026-06-05 08:31:15",
  "source": "同花顺热榜",
  "total": 100,
  "data": [
    {
      "rank": 1,
      "code": "000725",
      "name": "京东方A",
      "price": 6.43,
      "turnover": 15.15,
      "change_pct": 4.55,
      "hot_value": "3454387.0",
      "rank_chg": 1,
      "popularity_tag": "2天1板",
      "concept_tags": [
        "电子纸",
        "MicroLED概念"
      ],
      "analyse": "",
      "xueqiu_rank": 0,
      "browse_rank": 0
    },
    {
      "rank": 2,
      "code": "601991",
      "name": "大唐发电",
      "price": 7.93,
      "turnover": 6.46,
      "change_pct": -9.99,
      "hot_value": "3448780.0",
      "rank_chg": -1,
      "popularity_tag": "持续上榜",
      "concept_tags": [
        "绿色电力",
        "风电"
      ],
      "analyse": "",
      "xueqiu_rank": 0,
      "browse_rank": 0
    },
    {
      "rank": 3,
      "code": "600396",
      "name": "华电辽能",
      "price": 20.01,
      "turnover": 19.7,
      "change_pct": -8.92,
      "hot_value": "2749920.0",
      "rank_chg": 0,
      "popularity_tag": "",
      "concept_tags": [
        "超超临界发电",
        "绿色电力"
      ],
      "analyse": "",
      "xueqiu_rank": 0,
      "browse_rank": 0
    },
    {
      "rank": 4,
      "code": "300308",
      "name": "中际旭创",
      "price": 1179.99,
      "turnover": 4.28,
      "change_pct": -7.81,
      "hot_value": "2646404.0",
      "rank_chg": 0,
      "popularity_tag": "",
      "concept_tags": [
        "共封装光学(CPO)",
        "F5G概念"
      ],
      "analyse": "",
      "xueqiu_rank": 0,
      "browse_rank": 0
    },
    {
      "rank": 5,
      "code": "603890",
      "name": "春秋电子",
      "price": 31.24,
      "turnover": 31.8,
      "change_pct": 6.4,
      "hot_value": "2399469.0",
      "rank_chg": 0,
      "popularity_tag": "6天3板",
      "concept_tags": [
        "AI PC",
        "富士康概念"
      ],
      "analyse": "",
      "xueqiu_rank": 0,
      "browse_rank": 0
    },
    {
      "rank": 6,
      "code": "001896",
      "name": "豫能控股",
      "price": 19.88,
      "turnover": 19.64,
      "change_pct": -10.0,
      "hot_value": "2009308.0",
      "rank_chg": 0,
      "popularity_tag": "3天2板",
      "concept_tags": [
        "抽水蓄能",
        "超超临界发电"
      ],
      "analyse": "1、据同花顺iFinD数据，截至6月5日13时15分，电力板块下跌2.82%，火电板块下跌3.84%，豫能控股下跌7.51%，广西能源等多股跟跌，公司股价受板块整体回调影响。\n2、据公司2026年6月4日公告，公司股票此前连续三个交易日收盘价格涨幅偏离值累计达22.41%，公司提示股价存在累计涨幅异常的风险，并指出存在市场情绪过热、非理性炒作情形。据同花顺iFinD数据，豫能控股此前5个交易日累计上涨40.79%，今日下跌为超涨后回调。\n3、据同花顺iFinD数据，截至6月5日13时15分，豫能控股主力资金今日净流出5.14亿元。\n\n（免责声明：本内容由AI技术搜集公开信息总结生成，仅供参考，不构成投资建议，以上市公司公告为准）",
      "xueqiu_rank": 0,
      "browse_rank": 0
    },
    {
      "rank": 7,
      "code": "600487",
      "name": "亨通光电",
      "price": 96.12,
      "turnover": 10.26,
      "change_pct": -1.79,
      "hot_value": "1679470.0",
      "rank_chg": 0,
      "popularity_tag": "4天2板",
      "concept_tags": [
        "光纤概念",
        "F5G概念"
      ],
      "analyse": "",
      "xueqiu_rank": 0,
      "browse_rank": 0
    },
    {
      "rank": 8,
      "code": "603601",
      "name": "再升科技",
      "price": 16.49,
      "turnover": 24.4,
      "change_pct": 5.91,
      "hot_value": "1598925.0",
      "rank_chg": 0,
      "popularity_tag": "",
      "concept_tags": [
        "商业航天",
        "大飞机"
      ],
      "analyse": "",
      "xueqiu_rank": 0,
      "browse_rank": 0
    },
    {
      "rank": 9,
      "code": "601138",
      "name": "工业富联",
      "price": 74.06,
      "turnover": 1.32,
      "change_pct": -5.72,
      "hot_value": "1562236.0",
      "rank_chg": 0,
      "popularity_tag": "",
      "concept_tags": [
        "同花顺果指数",
        "共封装光学(CPO)"
      ],
      "analyse": "",
      "xueqiu_rank": 0,
      "browse_rank": 0
    },
    {
      "rank": 10,
      "code": "600584",
      "name": "长电科技",
      "price": 75.65,
      "turnover": 11.48,
      "change_pct": -5.53,
      "hot_value": "1498531.0",
      "rank_chg": 0,
      "popularity_tag": "持续上榜",
      "concept_tags": [
        "国家大基金持股",
        "先进封装"
      ],
      "analyse": "",
      "xueqiu_rank": 0,
      "browse_rank": 0
    },
    {
      "rank": 11,
      "code": "002579",
      "name": "中京电子",
      "price": 18.69,
      "turnover": 29.92,
      "change_pct": -9.32,
      "hot_value": "1434583.0",
      "rank_chg": 0,
      "popularity_tag": "9天5板",
      "concept_tags": [
        "AI PC",
        "PCB概念"
      ],
      "analyse": "",
      "xueqiu_rank": 0,
      "browse_rank": 0
    },
    {
      "rank": 12,
      "code": "002491",
      "name": "通鼎互联",
      "price": 24.82,
      "turnover": 25.26,
      "change_pct": -7.49,
      "hot_value": "1358336.0",
      "rank_chg": 0,
      "popularity_tag": "2天1板",
      "concept_tags": [
        "光纤概念",
        "5G"
      ],
      "analyse": "",
      "xueqiu_rank": 0,
      "browse_rank": 0
    },
    {
      "rank": 13,
      "code": "600522",
      "name": "中天科技",
      "price": 46.07,
      "turnover": 11.91,
      "change_pct": 0.02,
      "hot_value": "1339733.0",
      "rank_chg": 0,
      "popularity_tag": "",
      "concept_tags": [
        "光纤概念",
        "铜缆高速连接"
      ],
      "analyse": "",
      "xueqiu_rank": 0,
      "browse_rank": 0
    },
    {
      "rank": 14,
      "code": "603629",
      "name": "利通电子",
      "price": 180.38,
      "turnover": 13.08,
      "change_pct": -10.0,
      "hot_value": "1274992.0",
      "rank_chg": 0,
      "popularity_tag": "",
      "concept_tags": [
        "算力租赁",
        "英伟达概念"
      ],
      "analyse": "1、据2026年5月30日公告，公司股票于2026年4月14日至2026年5月29日连续30个交易日内收盘价格涨幅偏离值累计达200%，触及严重异常波动。公司多次提示股价短期涨幅较大，已累积巨大交易风险，存在市场情绪过热、非理性炒作及随时快速下跌的风险。\n2、据2026年5月30日公告，公司披露算力业务客户集中度高、存量设备均已出租导致增量空间有限、市场竞争激烈或致毛利率下滑、2026年净利润增速可能下降、资产负债率高达75.10%且或进一步攀升等多重经营风险。\n3、据同花顺iFinD数据，截至6月5日10时2分40秒，公司主力资金今日净流出2.41亿元。\n\n（免责声明：本内容由AI技术搜集公开信息总结生成，仅供参考，不构成投资建议，以上市公司公告为准）",
      "xueqiu_rank": 0,
      "browse_rank": 0
    },
    {
      "rank": 15,
      "code": "300136",
      "name": "信维通信",
      "price": 106.33,
      "turnover": 15.63,
      "change_pct": 8.5,
      "hot_value": "1246650.0",
      "rank_chg": 0,
      "popularity_tag": "",
      "concept_tags": [
        "同花顺果指数",
        "6G概念"
      ],
      "analyse": "",
      "xueqiu_rank": 0,
      "browse_rank": 0
    },
    {
      "rank": 16,
      "code": "600879",
      "name": "航天电子",
      "price": 21.54,
      "turnover": 7.76,
      "change_pct": 9.28,
      "hot_value": "1242762.0",
      "rank_chg": 0,
      "popularity_tag": "",
      "concept_tags": [
        "太赫兹",
        "军工信息化"
      ],
      "analyse": "",
      "xueqiu_rank": 0,
      "browse_rank": 0
    },
    {
      "rank": 17,
      "code": "000063",
      "name": "中兴通讯",
      "price": 39.13,
      "turnover": 11.51,
      "change_pct": 3.68,
      "hot_value": "1212616.0",
      "rank_chg": 1,
      "popularity_tag": "",
      "concept_tags": [
        "6G概念",
        "光纤概念"
      ],
      "analyse": "",
      "xueqiu_rank": 0,
      "browse_rank": 0
    },
    {
      "rank": 18,
      "code": "600726",
      "name": "华电能源",
      "price": 9.35,
      "turnover": 5.73,
      "change_pct": -10.01,
      "hot_value": "1211844.0",
      "rank_chg": 1,
      "popularity_tag": "10天5板",
      "concept_tags": [
        "超超临界发电",
        "煤炭概念"
      ],
      "analyse": "1、截至14点34分，电力板块震荡下行，广西能源、豫能控股跌停，华电能源跌近9%，华能蒙电、建投能源、晋控电力、粤电力A等大跌。\n2、据2026年5月30日及5月29日风险提示公告，公司最新滚动市盈率及市净率远高于行业平均水平，交易风险极大。\n3、据同花顺iFinD数据，截至6月5日9时38分，公司主力资金今日净流出1.86亿元。\n\n（免责声明：本内容由AI技术搜集公开信息总结生成，仅供参考，不构成投资建议，以上市公司公告为准）",
      "xueqiu_rank": 0,
      "browse_rank": 0
    },
    {
      "rank": 19,
      "code": "002050",
      "name": "三花智控",
      "price": 47.51,
      "turnover": 5.47,
      "change_pct": 1.06,
      "hot_value": "1197415.0",
      "rank_chg": -2,
      "popularity_tag": "",
      "concept_tags": [
        "人形机器人",
        "同花顺新质50"
      ],
      "analyse": "",
      "xueqiu_rank": 0,
      "browse_rank": 0
    },
    {
      "rank": 20,
      "code": "000636",
      "name": "风华高科",
      "price": 59.65,
      "turnover": 14.63,
      "change_pct": -6.06,
      "hot_value": "1159817.0",
      "rank_chg": 1,
      "popularity_tag": "",
      "concept_tags": [
        "超级电容",
        "共封装光学(CPO)"
      ],
      "analyse": "",
      "xueqiu_rank": 0,
      "browse_rank": 0
    },
    {
      "rank": 21,
      "code": "002384",
      "name": "东山精密",
      "price": 221.41,
      "turnover": 6.09,
      "change_pct": -6.89,
      "hot_value": "1159409.0",
      "rank_chg": -1,
      "popularity_tag": "",
      "concept_tags": [
        "共封装光学(CPO)",
        "光纤概念"
      ],
      "analyse": "",
      "xueqiu_rank": 0,
      "browse_rank": 0
    },
    {
      "rank": 22,
      "code": "002185",
      "name": "华天科技",
      "price": 18.08,
      "turnover": 12.31,
      "change_pct": -6.13,
      "hot_value": "1140314.0",
      "rank_chg": 0,
      "popularity_tag": "",
      "concept_tags": [
        "国家大基金持股",
        "先进封装"
      ],
      "analyse": "",
      "xueqiu_rank": 0,
      "browse_rank": 0
    },
    {
      "rank": 23,
      "code": "600745",
      "name": "*ST闻泰",
      "price": 21.39,
      "turnover": 9.14,
      "change_pct": 3.99,
      "hot_value": "1136513.0",
      "rank_chg": 0,
      "popularity_tag": "12天8板",
      "concept_tags": [
        "ST板块",
        "同花顺漂亮100"
      ],
      "analyse": "",
      "xueqiu_rank": 0,
      "browse_rank": 0
    },
    {
      "rank": 24,
      "code": "600105",
      "name": "永鼎股份",
      "price": 55.42,
      "turnover": 14.38,
      "change_pct": 2.08,
      "hot_value": "1116685.0",
      "rank_chg": 0,
      "popularity_tag": "",
      "concept_tags": [
        "共封装光学(CPO)",
        "光纤概念"
      ],
      "analyse": "",
      "xueqiu_rank": 0,
      "browse_rank": 0
    },
    {
      "rank": 25,
      "code": "002421",
      "name": "达实智能",
      "price": 5.21,
      "turnover": 38.9,
      "change_pct": 9.92,
      "hot_value": "1105839.0",
      "rank_chg": 0,
      "popularity_tag": "16天9板",
      "concept_tags": [
        "信创",
        "液冷服务器"
      ],
      "analyse": "1、据2026年6月4日达实智能官微，公司在6月3日举办的生态伙伴大会上展示了AI Agent 2.0的演进成果，仅用两个月从“1个超级智能体+5个场景智能体”快速迭代至“1个超级智能体+15个场景智能体”，全方位呈现了在“AI+物联网平台”领域的技术实力。\n2、据2026年4月29日投资者关系活动记录表，公司AIoT平台升级至7.1版本，推出“1个超级智能体+5个专业智能体”的本地部署方案，已在达实大厦落地应用，实现物业运维提效、员工办公自动化及能碳管理；2025年AIoT平台及AI应用签约金额达7847.14万元，下半年较上半年环比增长113.3%。\n3、据2026年4月29日投资者关系活动记录表，公司已有成熟的基于AIoT物联网平台的液冷全局优化节能控制系统方案，并已在深圳国能商贸云计算中心和深圳光明科学城大数据中心中应用，服务于20多个城市超50000个机架。\n\n（免责声明：本内容由AI技术搜集公开信息总结生成，仅供参考，不构成投资建议，以上市公司公告为准）",
      "xueqiu_rank": 0,
      "browse_rank": 0
    },
    {
      "rank": 26,
      "code": "688017",
      "name": "绿的谐波",
      "price": 393.0,
      "turnover": 12.21,
      "change_pct": 20.0,
      "hot_value": "1102513.0",
      "rank_chg": 0,
      "popularity_tag": "首板涨停",
      "concept_tags": [
        "减速器",
        "人形机器人"
      ],
      "analyse": "行业原因：\n1、宇树科技于6月1日通过科创板IPO上会，国产人形机器人企业的资本化进程加速。\n2、英伟达近日发布NVIDIA Cosmos 3——面向物理AI的开放世界基础模型。黄仁勋表示，得益于多模态推理语言、视觉和世界模型领域的多项突破，物理AI爆发的时代已近在眼前。\n公司原因：\n1、据券商中国6月5日报道，绿的谐波涨停可能与互联网上一个贴子有关。署名为“Serenity”的财经博主发文称：绿的谐波是我在布局人形机器人赛道时最青睐的中国上市标的。资料显示，“Serenity”是近期很火的一个超级散户，半年收益达4502.45%。\n2、据2026年4月23日年报，公司进一步巩固了在具身智能场景谐波减速器的领先地位，客户数量和产品出货量大幅度提高，市场占有率全球领先。\n3、据2026年4月23日年报，公司是国内谐波减速器行业龙头，全球唯一实现精密谐波减速器全零部件自主供应的制造商，打破了国际品牌垄断，产品已实现国际头部机器人客户批量交付，并推出了专用于具身智能场景的轻量化专用关节模组。\n\n（免责声明：本内容由AI技术搜集公开信息总结生成，仅供参考，不构成投资建议，以上市公司公告为准）",
      "xueqiu_rank": 0,
      "browse_rank": 0
    },
    {
      "rank": 27,
      "code": "603986",
      "name": "兆易创新",
      "price": 488.0,
      "turnover": 8.19,
      "change_pct": -7.8,
      "hot_value": "1055353.0",
      "rank_chg": 0,
      "popularity_tag": "",
      "concept_tags": [
        "存储芯片",
        "汽车芯片"
      ],
      "analyse": "",
      "xueqiu_rank": 0,
      "browse_rank": 0
    },
    {
      "rank": 28,
      "code": "600578",
      "name": "京能电力",
      "price": 8.46,
      "turnover": 4.94,
      "change_pct": -9.62,
      "hot_value": "967558.0",
      "rank_chg": 0,
      "popularity_tag": "",
      "concept_tags": [
        "超超临界发电",
        "绿色电力"
      ],
      "analyse": "",
      "xueqiu_rank": 0,
      "browse_rank": 0
    },
    {
      "rank": 29,
      "code": "600498",
      "name": "烽火通信",
      "price": 56.48,
      "turnover": 16.31,
      "change_pct": 7.07,
      "hot_value": "959216.0",
      "rank_chg": 0,
      "popularity_tag": "",
      "concept_tags": [
        "光纤概念",
        "F5G概念"
      ],
      "analyse": "",
      "xueqiu_rank": 0,
      "browse_rank": 0
    },
    {
      "rank": 30,
      "code": "600403",
      "name": "大有能源",
      "price": 8.14,
      "turnover": 8.91,
      "change_pct": 10.0,
      "hot_value": "935972.0",
      "rank_chg": 0,
      "popularity_tag": "5天5板",
      "concept_tags": [
        "煤炭概念",
        "国企改革"
      ],
      "analyse": "1、据期货日报2026年6月4日报道，焦煤期货主力合约自5月22日以来累计上涨近20%，受安监影响供应收缩，山西现货竞拍价格跳涨；据2026年4月3日年报，公司主要从事原煤开采、煤炭批发经营、煤炭洗选加工，主要产品包含焦煤。\n2、据2026年4月3日年报，公司主营业务为原煤开采、煤炭批发经营，2025年商品煤产量1089.44万吨。\n3、据最终控制人信息，公司最终控制人为河南省人民政府国有资产监督管理委员会；据2026年1月17日收购报告书，河南省国资委以河南能源集团100%股权对平煤神马集团增资，完成后平煤神马集团间接持有公司84.50%股份。\n\n（免责声明：本内容由AI技术搜集公开信息总结生成，仅供参考，不构成投资建议，以上市公司公告为准）",
      "xueqiu_rank": 0,
      "browse_rank": 0
    },
    {
      "rank": 31,
      "code": "002281",
      "name": "光迅科技",
      "price": 227.58,
      "turnover": 9.44,
      "change_pct": 3.18,
      "hot_value": "908590.0",
      "rank_chg": 0,
      "popularity_tag": "",
      "concept_tags": [
        "F5G概念",
        "光纤概念"
      ],
      "analyse": "",
      "xueqiu_rank": 0,
      "browse_rank": 0
    },
    {
      "rank": 32,
      "code": "002475",
      "name": "立讯精密",
      "price": 68.77,
      "turnover": 3.51,
      "change_pct": -7.8,
      "hot_value": "888017.0",
      "rank_chg": 0,
      "popularity_tag": "",
      "concept_tags": [
        "同花顺果指数",
        "铜缆高速连接"
      ],
      "analyse": "",
      "xueqiu_rank": 0,
      "browse_rank": 0
    },
    {
      "rank": 33,
      "code": "300433",
      "name": "蓝思科技",
      "price": 45.61,
      "turnover": 4.63,
      "change_pct": 4.51,
      "hot_value": "882597.0",
      "rank_chg": 0,
      "popularity_tag": "",
      "concept_tags": [
        "同花顺果指数",
        "AI手机"
      ],
      "analyse": "",
      "xueqiu_rank": 0,
      "browse_rank": 0
    },
    {
      "rank": 34,
      "code": "600367",
      "name": "红星发展",
      "price": 49.5,
      "turnover": 22.14,
      "change_pct": 5.36,
      "hot_value": "871738.0",
      "rank_chg": 2,
      "popularity_tag": "9天6板",
      "concept_tags": [
        "小金属概念",
        "钠离子电池"
      ],
      "analyse": "",
      "xueqiu_rank": 0,
      "browse_rank": 0
    },
    {
      "rank": 35,
      "code": "600667",
      "name": "太极实业",
      "price": 16.15,
      "turnover": 20.49,
      "change_pct": -1.28,
      "hot_value": "869626.0",
      "rank_chg": 0,
      "popularity_tag": "4天2板",
      "concept_tags": [
        "存储芯片",
        "先进封装"
      ],
      "analyse": "",
      "xueqiu_rank": 0,
      "browse_rank": 0
    },
    {
      "rank": 36,
      "code": "002251",
      "name": "步步高",
      "price": 4.86,
      "turnover": 15.94,
      "change_pct": 9.95,
      "hot_value": "849505.0",
      "rank_chg": -2,
      "popularity_tag": "首板涨停",
      "concept_tags": [
        "免税店",
        "预制菜"
      ],
      "analyse": "行业原因：\n科技板块调整背景下，资金寻求低位避险资产。中信建投此前指出，2025年至今，消费板块整体居后，市场对于消费下行的预期尚未充分反馈，但估值和业绩接近理性区间，机构配置也处于低位。\n公司原因：\n1、据2026年6月4日互动易及2026年5月28日异常波动公告，步步高超市长沙区域6家核心门店线上业务已于2026年5月8日开放。\n2、据2026年5月28日异常波动公告及2025年年报，公司已完成在营22家超市门店的胖东来模式调改，通过商品、服务与组织的系统性重构恢复顾客口碑。\n3、据2026年4月23日年报，公司主营商品零售，以超市、百货双业态驱动，是湖南省连锁零售龙头企业；2026年一季度营收13.13亿元，同比增长13.67%。\n\n（免责声明：本内容由AI技术搜集公开信息总结生成，仅供参考，不构成投资建议，以上市公司公告为准）",
      "xueqiu_rank": 0,
      "browse_rank": 0
    },
    {
      "rank": 37,
      "code": "002969",
      "name": "嘉美包装",
      "price": 16.79,
      "turnover": 10.2,
      "change_pct": -9.97,
      "hot_value": "845360.0",
      "rank_chg": 6,
      "popularity_tag": "",
      "concept_tags": [
        "啤酒概念",
        "海峡两岸"
      ],
      "analyse": "1、6月5日，追觅科技创始人兼CEO俞浩微博主页显示：“因违反相关法律法规，该用户目前处于禁言状态。”\n2、据财联社6月5日报道，今日有消息称，长三角某市辖区正在要求统计辖区内企业与追觅科技已开展合作的情况，包括但不限于：合作项目、总体规模、资金投入、财政及国资投入情况、目前经营情况等。该地方人士回应记者称，系市里统一部署，其所在区域初排下来没有相关的情况。\n3、2026年6月5日，嘉美包装在披露控股权变更完成的公告后复牌，追觅创始人俞浩正式入主嘉美包装。据2026年5月12日机构调研，实际控制人俞浩明确承诺取得控制权后36个月内不会向上市公司注入任何资产，且目前不存在资产注入计划，公司与追觅关联企业业务无协同。\n\n（免责声明：本内容由AI技术搜集公开信息总结生成，仅供参考，不构成投资建议，以上市公司公告为准）",
      "xueqiu_rank": 0,
      "browse_rank": 0
    },
    {
      "rank": 38,
      "code": "002463",
      "name": "沪电股份",
      "price": 133.22,
      "turnover": 4.97,
      "change_pct": -5.4,
      "hot_value": "839183.0",
      "rank_chg": -1,
      "popularity_tag": "",
      "concept_tags": [
        "PCB概念",
        "毫米波雷达"
      ],
      "analyse": "",
      "xueqiu_rank": 0,
      "browse_rank": 0
    },
    {
      "rank": 39,
      "code": "603773",
      "name": "沃格光电",
      "price": 132.4,
      "turnover": 15.92,
      "change_pct": 8.17,
      "hot_value": "832901.0",
      "rank_chg": 0,
      "popularity_tag": "",
      "concept_tags": [
        "MicroLED概念",
        "MiniLED"
      ],
      "analyse": "",
      "xueqiu_rank": 0,
      "browse_rank": 0
    },
    {
      "rank": 40,
      "code": "600863",
      "name": "华能蒙电",
      "price": 6.23,
      "turnover": 6.74,
      "change_pct": -9.45,
      "hot_value": "826552.0",
      "rank_chg": -2,
      "popularity_tag": "",
      "concept_tags": [
        "超超临界发电",
        "煤炭概念"
      ],
      "analyse": "",
      "xueqiu_rank": 0,
      "browse_rank": 0
    },
    {
      "rank": 41,
      "code": "300502",
      "name": "新易盛",
      "price": 748.0,
      "turnover": 4.93,
      "change_pct": -3.6,
      "hot_value": "806703.0",
      "rank_chg": -1,
      "popularity_tag": "",
      "concept_tags": [
        "共封装光学(CPO)",
        "芯片概念"
      ],
      "analyse": "",
      "xueqiu_rank": 0,
      "browse_rank": 0
    },
    {
      "rank": 42,
      "code": "002361",
      "name": "神剑股份",
      "price": 16.81,
      "turnover": 18.36,
      "change_pct": 10.01,
      "hot_value": "805818.0",
      "rank_chg": -1,
      "popularity_tag": "首板涨停",
      "concept_tags": [
        "航空发动机",
        "卫星导航"
      ],
      "analyse": "行业原因：\nSpaceX已启动IPO路演，目标估值1.75万亿美元，募资规模750亿美元，计划6月12日挂牌上市。有分析称，此举或重塑商业航天板块估值体系。\n公司原因：\n1、据2026年2月9日及2025年12月30日异常波动公告，公司关注到市场对其商业航天业务关注度较高，公司航空航天类产品包括卫星复合材料零部件等，但2025年前三季度商业航天应用领域收入仅371.24万元，占营收0.20%。\n2、据2026年4月28日年报，2025年公司聚酯树脂销售23.29万吨，同比增长13.45%，公司是国内粉末涂料用聚酯树脂行业领军者。\n3、据2026年5月8日投资者关系活动记录表，公司坚持“化工新材料+高端装备制造”双主业发展战略；公司最终控制人为芜湖市人民政府国有资产监督管理委员会。\n\n（免责声明：本内容由AI技术搜集公开信息总结生成，仅供参考，不构成投资建议，以上市公司公告为准）",
      "xueqiu_rank": 0,
      "browse_rank": 0
    },
    {
      "rank": 43,
      "code": "600869",
      "name": "远东股份",
      "price": 28.51,
      "turnover": 7.9,
      "change_pct": 7.58,
      "hot_value": "801860.0",
      "rank_chg": 1,
      "popularity_tag": "",
      "concept_tags": [
        "光纤概念",
        "铜缆高速连接"
      ],
      "analyse": "",
      "xueqiu_rank": 0,
      "browse_rank": 0
    },
    {
      "rank": 44,
      "code": "002156",
      "name": "通富微电",
      "price": 66.84,
      "turnover": 9.75,
      "change_pct": -5.99,
      "hot_value": "789813.0",
      "rank_chg": -2,
      "popularity_tag": "",
      "concept_tags": [
        "国家大基金持股",
        "存储芯片"
      ],
      "analyse": "",
      "xueqiu_rank": 0,
      "browse_rank": 0
    },
    {
      "rank": 45,
      "code": "000681",
      "name": "视觉中国",
      "price": 24.31,
      "turnover": 17.46,
      "change_pct": 4.78,
      "hot_value": "778839.0",
      "rank_chg": 1,
      "popularity_tag": "",
      "concept_tags": [
        "快手概念",
        "AI视频"
      ],
      "analyse": "",
      "xueqiu_rank": 0,
      "browse_rank": 0
    },
    {
      "rank": 46,
      "code": "600118",
      "name": "中国卫星",
      "price": 84.95,
      "turnover": 6.48,
      "change_pct": 5.82,
      "hot_value": "777587.0",
      "rank_chg": -1,
      "popularity_tag": "",
      "concept_tags": [
        "国产航母",
        "卫星导航"
      ],
      "analyse": "",
      "xueqiu_rank": 0,
      "browse_rank": 0
    },
    {
      "rank": 47,
      "code": "000539",
      "name": "粤电力A",
      "price": 8.25,
      "turnover": 11.07,
      "change_pct": -10.03,
      "hot_value": "759240.0",
      "rank_chg": 1,
      "popularity_tag": "8天4板",
      "concept_tags": [
        "超超临界发电",
        "绿色电力"
      ],
      "analyse": "1、据2026年6月2日异动公告，公司股票在2026年5月27日至6月1日期间短期快速上涨，累计涨幅达40.05%，存在市场情绪过热及非理性炒作情形，短期回调压力较大。\n2、据同花顺iFinD数据，截至6月5日14时17分，电力板块下跌3.49%，火电板块下跌4.77%；据证券时报网6月5日报道，电力板块震荡下行，广西能源、豫能控股逼近跌停，粤电力A等大跌，公司股价受板块整体调整拖累。\n3、据2026年6月2日异动公告，公司澄清其克拉玛依项目算力收入占总营收0.02%，无扩大算力规模规划，发电业务与韶关算力集群无直接关联，此前市场热炒的算力题材落空。\n4、据同花顺iFinD数据，截至6月5日14时17分，公司主力资金今日净流出2.62亿元。\n\n（免责声明：本内容由AI技术搜集公开信息总结生成，仅供参考，不构成投资建议，以上市公司公告为准）",
      "xueqiu_rank": 0,
      "browse_rank": 0
    },
    {
      "rank": 48,
      "code": "600183",
      "name": "生益科技",
      "price": 137.36,
      "turnover": 3.03,
      "change_pct": -4.05,
      "hot_value": "753790.0",
      "rank_chg": -1,
      "popularity_tag": "",
      "concept_tags": [
        "PCB概念",
        "共封装光学(CPO)"
      ],
      "analyse": "",
      "xueqiu_rank": 0,
      "browse_rank": 0
    },
    {
      "rank": 49,
      "code": "300476",
      "name": "胜宏科技",
      "price": 338.9,
      "turnover": 6.39,
      "change_pct": -7.59,
      "hot_value": "747678.0",
      "rank_chg": 0,
      "popularity_tag": "",
      "concept_tags": [
        "PCB概念",
        "共封装光学(CPO)"
      ],
      "analyse": "",
      "xueqiu_rank": 0,
      "browse_rank": 0
    },
    {
      "rank": 50,
      "code": "002149",
      "name": "西部材料",
      "price": 65.0,
      "turnover": 13.41,
      "change_pct": 3.98,
      "hot_value": "717888.0",
      "rank_chg": 0,
      "popularity_tag": "",
      "concept_tags": [
        "航空发动机",
        "卫星导航"
      ],
      "analyse": "",
      "xueqiu_rank": 0,
      "browse_rank": 0
    },
    {
      "rank": 51,
      "code": "600255",
      "name": "鑫科材料",
      "price": 4.49,
      "turnover": 32.54,
      "change_pct": -7.04,
      "hot_value": "685804.0",
      "rank_chg": 2,
      "popularity_tag": "4天3板",
      "concept_tags": [
        "金属铜",
        "铜缆高速连接"
      ],
      "analyse": "",
      "xueqiu_rank": 0,
      "browse_rank": 0
    },
    {
      "rank": 52,
      "code": "002896",
      "name": "中大力德",
      "price": 86.77,
      "turnover": 14.61,
      "change_pct": 10.0,
      "hot_value": "684782.0",
      "rank_chg": 0,
      "popularity_tag": "首板涨停",
      "concept_tags": [
        "减速器",
        "人形机器人"
      ],
      "analyse": "行业原因：\n1、宇树科技于6月1日通过科创板IPO上会，国产人形机器人企业的资本化进程加速。\n2、英伟达近日发布NVIDIA Cosmos 3——面向物理AI的开放世界基础模型。黄仁勋表示，得益于多模态推理语言、视觉和世界模型领域的多项突破，物理AI爆发的时代已近在眼前。\n公司原因：\n1、据2026年4月16日年报，公司作为全品类精密减速器制造商，专门开发了ZCSD-14、ZSHF-14等型号谐波减速器，主要运用于人形机器人的关节传动部位；人形机器人产业化加速有望为减速器行业带来巨大增量，公司将深度受益。\n2、据2026年4月16日年报，公司是国内少数实现行星减速器、RV减速器、谐波减速器三大品类批量生产的企业之一，并形成了“减速器+电机+驱动”一体化的产品架构，产品广泛应用于机器人等领域，终端客户包括智元机器人、傅利叶等。\n3、据2026年4月28日2025年度业绩说明会及2026年4月16日公告，公司正加速国际化布局，拟在越南和德国设立子公司，以增强服务能力，拓展海外市场份额，强化国际竞争力。\n\n（免责声明：本内容由AI技术搜集公开信息总结生成，仅供参考，不构成投资建议，以上市公司公告为准）",
      "xueqiu_rank": 0,
      "browse_rank": 0
    },
    {
      "rank": 53,
      "code": "603667",
      "name": "五洲新春",
      "price": 74.34,
      "turnover": 13.22,
      "change_pct": 3.48,
      "hot_value": "676234.0",
      "rank_chg": -2,
      "popularity_tag": "",
      "concept_tags": [
        "减速器",
        "人形机器人"
      ],
      "analyse": "",
      "xueqiu_rank": 0,
      "browse_rank": 0
    },
    {
      "rank": 54,
      "code": "000988",
      "name": "华工科技",
      "price": 157.2,
      "turnover": 9.17,
      "change_pct": -0.73,
      "hot_value": "671870.0",
      "rank_chg": 0,
      "popularity_tag": "",
      "concept_tags": [
        "共封装光学(CPO)",
        "F5G概念"
      ],
      "analyse": "",
      "xueqiu_rank": 0,
      "browse_rank": 0
    },
    {
      "rank": 55,
      "code": "600186",
      "name": "莲花控股",
      "price": 10.13,
      "turnover": 18.72,
      "change_pct": 6.97,
      "hot_value": "668438.0",
      "rank_chg": 1,
      "popularity_tag": "",
      "concept_tags": [
        "算力租赁",
        "东数西算(算力)"
      ],
      "analyse": "",
      "xueqiu_rank": 0,
      "browse_rank": 0
    },
    {
      "rank": 56,
      "code": "603330",
      "name": "天洋新材",
      "price": 8.61,
      "turnover": 33.87,
      "change_pct": -8.5,
      "hot_value": "666527.0",
      "rank_chg": 4,
      "popularity_tag": "5天4板",
      "concept_tags": [
        "POE胶膜",
        "消费电子概念"
      ],
      "analyse": "",
      "xueqiu_rank": 0,
      "browse_rank": 0
    },
    {
      "rank": 57,
      "code": "601899",
      "name": "紫金矿业",
      "price": 29.63,
      "turnover": 1.32,
      "change_pct": -2.34,
      "hot_value": "665815.0",
      "rank_chg": -2,
      "popularity_tag": "",
      "concept_tags": [
        "金属铅",
        "黄金概念"
      ],
      "analyse": "",
      "xueqiu_rank": 0,
      "browse_rank": 0
    },
    {
      "rank": 58,
      "code": "600172",
      "name": "黄河旋风",
      "price": 13.43,
      "turnover": 18.01,
      "change_pct": -7.25,
      "hot_value": "650205.0",
      "rank_chg": -1,
      "popularity_tag": "",
      "concept_tags": [
        "培育钻石",
        "第三代半导体"
      ],
      "analyse": "",
      "xueqiu_rank": 0,
      "browse_rank": 0
    },
    {
      "rank": 59,
      "code": "600707",
      "name": "彩虹股份",
      "price": 11.71,
      "turnover": 11.0,
      "change_pct": 6.94,
      "hot_value": "642995.0",
      "rank_chg": -1,
      "popularity_tag": "",
      "concept_tags": [
        "OLED",
        "人民币贬值受益"
      ],
      "analyse": "",
      "xueqiu_rank": 0,
      "browse_rank": 0
    },
    {
      "rank": 60,
      "code": "002436",
      "name": "兴森科技",
      "price": 37.9,
      "turnover": 12.2,
      "change_pct": -7.27,
      "hot_value": "641080.0",
      "rank_chg": -1,
      "popularity_tag": "",
      "concept_tags": [
        "PCB概念",
        "共封装光学(CPO)"
      ],
      "analyse": "",
      "xueqiu_rank": 0,
      "browse_rank": 0
    },
    {
      "rank": 61,
      "code": "002585",
      "name": "双星新材",
      "price": 11.82,
      "turnover": 33.39,
      "change_pct": 0.17,
      "hot_value": "624483.0",
      "rank_chg": 0,
      "popularity_tag": "2天1板",
      "concept_tags": [
        "PET铜箔",
        "OLED"
      ],
      "analyse": "",
      "xueqiu_rank": 0,
      "browse_rank": 0
    },
    {
      "rank": 62,
      "code": "600162",
      "name": "香江控股",
      "price": 3.44,
      "turnover": 12.06,
      "change_pct": 0.58,
      "hot_value": "603706.0",
      "rank_chg": 1,
      "popularity_tag": "10天6板",
      "concept_tags": [
        "物业管理",
        "民营医院"
      ],
      "analyse": "",
      "xueqiu_rank": 0,
      "browse_rank": 0
    },
    {
      "rank": 63,
      "code": "002015",
      "name": "协鑫能科",
      "price": 22.32,
      "turnover": 9.21,
      "change_pct": -7.46,
      "hot_value": "602615.0",
      "rank_chg": -1,
      "popularity_tag": "",
      "concept_tags": [
        "抽水蓄能",
        "华为数字能源"
      ],
      "analyse": "",
      "xueqiu_rank": 0,
      "browse_rank": 0
    },
    {
      "rank": 64,
      "code": "603005",
      "name": "晶方科技",
      "price": 45.8,
      "turnover": 20.85,
      "change_pct": 2.74,
      "hot_value": "574525.0",
      "rank_chg": 1,
      "popularity_tag": "2天1板",
      "concept_tags": [
        "先进封装",
        "第三代半导体"
      ],
      "analyse": "",
      "xueqiu_rank": 0,
      "browse_rank": 0
    },
    {
      "rank": 65,
      "code": "300394",
      "name": "天孚通信",
      "price": 457.0,
      "turnover": 6.06,
      "change_pct": -4.88,
      "hot_value": "570857.0",
      "rank_chg": -1,
      "popularity_tag": "",
      "concept_tags": [
        "共封装光学(CPO)",
        "光纤概念"
      ],
      "analyse": "",
      "xueqiu_rank": 0,
      "browse_rank": 0
    },
    {
      "rank": 66,
      "code": "600703",
      "name": "三安光电",
      "price": 16.91,
      "turnover": 9.24,
      "change_pct": -0.88,
      "hot_value": "568469.0",
      "rank_chg": 0,
      "popularity_tag": "2天1板",
      "concept_tags": [
        "MicroLED概念",
        "第三代半导体"
      ],
      "analyse": "",
      "xueqiu_rank": 0,
      "browse_rank": 0
    },
    {
      "rank": 67,
      "code": "601869",
      "name": "长飞光纤",
      "price": 441.67,
      "turnover": 5.0,
      "change_pct": -3.12,
      "hot_value": "559507.0",
      "rank_chg": 0,
      "popularity_tag": "",
      "concept_tags": [
        "光纤概念",
        "铜缆高速连接"
      ],
      "analyse": "",
      "xueqiu_rank": 0,
      "browse_rank": 0
    },
    {
      "rank": 68,
      "code": "000070",
      "name": "特发信息",
      "price": 19.92,
      "turnover": 20.86,
      "change_pct": 7.5,
      "hot_value": "539885.0",
      "rank_chg": 0,
      "popularity_tag": "",
      "concept_tags": [
        "光纤概念",
        "F5G概念"
      ],
      "analyse": "",
      "xueqiu_rank": 0,
      "browse_rank": 0
    },
    {
      "rank": 69,
      "code": "002428",
      "name": "云南锗业",
      "price": 85.5,
      "turnover": 12.54,
      "change_pct": -3.51,
      "hot_value": "531817.0",
      "rank_chg": 0,
      "popularity_tag": "",
      "concept_tags": [
        "光纤概念",
        "第三代半导体"
      ],
      "analyse": "",
      "xueqiu_rank": 0,
      "browse_rank": 0
    },
    {
      "rank": 70,
      "code": "300058",
      "name": "蓝色光标",
      "price": 15.49,
      "turnover": 7.97,
      "change_pct": -2.64,
      "hot_value": "529711.0",
      "rank_chg": 0,
      "popularity_tag": "",
      "concept_tags": [
        "快手概念",
        "小红书概念"
      ],
      "analyse": "",
      "xueqiu_rank": 0,
      "browse_rank": 0
    },
    {
      "rank": 71,
      "code": "002636",
      "name": "金安国纪",
      "price": 58.16,
      "turnover": 12.25,
      "change_pct": 7.7,
      "hot_value": "526175.0",
      "rank_chg": 1,
      "popularity_tag": "",
      "concept_tags": [
        "PCB概念",
        "2025年报预增"
      ],
      "analyse": "",
      "xueqiu_rank": 0,
      "browse_rank": 0
    },
    {
      "rank": 72,
      "code": "300285",
      "name": "国瓷材料",
      "price": 65.18,
      "turnover": 16.47,
      "change_pct": 1.84,
      "hot_value": "524336.0",
      "rank_chg": -1,
      "popularity_tag": "",
      "concept_tags": [
        "共封装光学(CPO)",
        "5G"
      ],
      "analyse": "",
      "xueqiu_rank": 0,
      "browse_rank": 0
    },
    {
      "rank": 73,
      "code": "000100",
      "name": "TCL科技",
      "price": 4.89,
      "turnover": 9.85,
      "change_pct": -0.61,
      "hot_value": "518682.0",
      "rank_chg": 3,
      "popularity_tag": "",
      "concept_tags": [
        "MicroLED概念",
        "柔性屏(折叠屏)"
      ],
      "analyse": "",
      "xueqiu_rank": 0,
      "browse_rank": 0
    },
    {
      "rank": 74,
      "code": "002747",
      "name": "埃斯顿",
      "price": 31.02,
      "turnover": 12.27,
      "change_pct": 5.19,
      "hot_value": "515917.0",
      "rank_chg": 0,
      "popularity_tag": "",
      "concept_tags": [
        "人形机器人",
        "工业母机"
      ],
      "analyse": "",
      "xueqiu_rank": 0,
      "browse_rank": 0
    },
    {
      "rank": 75,
      "code": "600580",
      "name": "卧龙电驱",
      "price": 40.0,
      "turnover": 5.59,
      "change_pct": 2.99,
      "hot_value": "514394.0",
      "rank_chg": -2,
      "popularity_tag": "",
      "concept_tags": [
        "人形机器人",
        "特斯拉概念"
      ],
      "analyse": "",
      "xueqiu_rank": 0,
      "browse_rank": 0
    },
    {
      "rank": 76,
      "code": "600693",
      "name": "东百集团",
      "price": 10.35,
      "turnover": 13.5,
      "change_pct": 5.29,
      "hot_value": "504655.0",
      "rank_chg": -1,
      "popularity_tag": "",
      "concept_tags": [
        "免税店",
        "IP经济(谷子经济)"
      ],
      "analyse": "",
      "xueqiu_rank": 0,
      "browse_rank": 0
    },
    {
      "rank": 77,
      "code": "600821",
      "name": "金开新能",
      "price": 8.05,
      "turnover": 12.34,
      "change_pct": -6.61,
      "hot_value": "503975.0",
      "rank_chg": 0,
      "popularity_tag": "",
      "concept_tags": [
        "华为数字能源",
        "算力租赁"
      ],
      "analyse": "",
      "xueqiu_rank": 0,
      "browse_rank": 0
    },
    {
      "rank": 78,
      "code": "000547",
      "name": "航天发展",
      "price": 20.47,
      "turnover": 8.82,
      "change_pct": 2.86,
      "hot_value": "500528.0",
      "rank_chg": 0,
      "popularity_tag": "",
      "concept_tags": [
        "军工信息化",
        "卫星导航"
      ],
      "analyse": "",
      "xueqiu_rank": 0,
      "browse_rank": 0
    },
    {
      "rank": 79,
      "code": "300319",
      "name": "麦捷科技",
      "price": 22.28,
      "turnover": 31.95,
      "change_pct": 14.43,
      "hot_value": "496670.0",
      "rank_chg": 1,
      "popularity_tag": "",
      "concept_tags": [
        "共封装光学(CPO)",
        "存储芯片"
      ],
      "analyse": "",
      "xueqiu_rank": 0,
      "browse_rank": 0
    },
    {
      "rank": 80,
      "code": "603938",
      "name": "三孚股份",
      "price": 52.82,
      "turnover": 12.38,
      "change_pct": 10.0,
      "hot_value": "494229.0",
      "rank_chg": -1,
      "popularity_tag": "3天2板",
      "concept_tags": [
        "光纤概念",
        "存储芯片"
      ],
      "analyse": "行业原因：\n据央视财经6月4日报道，受AI算力建设驱动，光纤光缆企业的订单饱满。江苏苏州一个光通信科技园区内，产线负责人介绍，自2025年4季度以来，企业就已经满负荷生产，目前订单排产已到2027年。\n公司原因：\n1、据2026年5月21日投资者关系活动记录表，公司高纯四氯化硅产品目前基本满负荷运行，产能3万吨/年，下游主要应用于光纤预制棒；据2025年年报，公司已实现PCVD芯棒工艺规模化供应，9N级产品销往欧洲市场。\n2、据2025年6月30日互动易，公司电子级二氯二氢硅产品已覆盖下游国内存储芯片、逻辑芯片等领域，已实现向部分国内龙头存储厂商批量稳定供应。\n3、据2025年年报，公司是全国范围内产量较大及供货稳定的三氯氢硅、高纯四氯化硅、氢氧化钾生产企业，形成“四硅-三气-两钾”生产系统；2026年一季度营收6.47亿元，同比增长30.91%。\n\n（免责声明：本内容由AI技术搜集公开信息总结生成，仅供参考，不构成投资建议，以上市公司公告为准）",
      "xueqiu_rank": 0,
      "browse_rank": 0
    },
    {
      "rank": 81,
      "code": "000021",
      "name": "深科技",
      "price": 38.13,
      "turnover": 8.66,
      "change_pct": -3.91,
      "hot_value": "486997.0",
      "rank_chg": 0,
      "popularity_tag": "",
      "concept_tags": [
        "存储芯片",
        "先进封装"
      ],
      "analyse": "",
      "xueqiu_rank": 0,
      "browse_rank": 0
    },
    {
      "rank": 82,
      "code": "605358",
      "name": "立昂微",
      "price": 66.77,
      "turnover": 15.24,
      "change_pct": 4.49,
      "hot_value": "479648.0",
      "rank_chg": 1,
      "popularity_tag": "2天1板",
      "concept_tags": [
        "汽车芯片",
        "第三代半导体"
      ],
      "analyse": "",
      "xueqiu_rank": 0,
      "browse_rank": 0
    },
    {
      "rank": 83,
      "code": "000767",
      "name": "晋控电力",
      "price": 5.34,
      "turnover": 14.44,
      "change_pct": -6.97,
      "hot_value": "477081.0",
      "rank_chg": 1,
      "popularity_tag": "",
      "concept_tags": [
        "超超临界发电",
        "绿色电力"
      ],
      "analyse": "",
      "xueqiu_rank": 0,
      "browse_rank": 0
    },
    {
      "rank": 84,
      "code": "002031",
      "name": "巨轮智能",
      "price": 6.67,
      "turnover": 14.01,
      "change_pct": 3.41,
      "hot_value": "474075.0",
      "rank_chg": -2,
      "popularity_tag": "",
      "concept_tags": [
        "减速器",
        "人形机器人"
      ],
      "analyse": "",
      "xueqiu_rank": 0,
      "browse_rank": 0
    },
    {
      "rank": 85,
      "code": "300274",
      "name": "阳光电源",
      "price": 153.75,
      "turnover": 5.29,
      "change_pct": -6.45,
      "hot_value": "461567.0",
      "rank_chg": 0,
      "popularity_tag": "",
      "concept_tags": [
        "宁德时代概念",
        "氢能源"
      ],
      "analyse": "",
      "xueqiu_rank": 0,
      "browse_rank": 0
    },
    {
      "rank": 86,
      "code": "002570",
      "name": "贝因美",
      "price": 5.6,
      "turnover": 15.64,
      "change_pct": -2.1,
      "hot_value": "452164.0",
      "rank_chg": 4,
      "popularity_tag": "2天1板",
      "concept_tags": [
        "乳业",
        "网红经济"
      ],
      "analyse": "",
      "xueqiu_rank": 0,
      "browse_rank": 0
    },
    {
      "rank": 87,
      "code": "002181",
      "name": "粤传媒",
      "price": 15.04,
      "turnover": 8.71,
      "change_pct": -1.89,
      "hot_value": "449225.0",
      "rank_chg": -1,
      "popularity_tag": "",
      "concept_tags": [
        "足球概念",
        "广东自贸区"
      ],
      "analyse": "",
      "xueqiu_rank": 0,
      "browse_rank": 0
    },
    {
      "rank": 88,
      "code": "600378",
      "name": "昊华科技",
      "price": 46.6,
      "turnover": 6.93,
      "change_pct": 6.98,
      "hot_value": "448099.0",
      "rank_chg": 1,
      "popularity_tag": "",
      "concept_tags": [
        "PVDF概念",
        "氟化工概念"
      ],
      "analyse": "",
      "xueqiu_rank": 0,
      "browse_rank": 0
    },
    {
      "rank": 89,
      "code": "002081",
      "name": "金螳螂",
      "price": 5.78,
      "turnover": 11.9,
      "change_pct": -4.46,
      "hot_value": "446369.0",
      "rank_chg": -2,
      "popularity_tag": "",
      "concept_tags": [
        "新型城镇化",
        "装配式建筑"
      ],
      "analyse": "",
      "xueqiu_rank": 0,
      "browse_rank": 0
    },
    {
      "rank": 90,
      "code": "002565",
      "name": "顺灏股份",
      "price": 15.34,
      "turnover": 12.29,
      "change_pct": 5.28,
      "hot_value": "437365.0",
      "rank_chg": 1,
      "popularity_tag": "",
      "concept_tags": [
        "卫星导航",
        "商业航天"
      ],
      "analyse": "",
      "xueqiu_rank": 0,
      "browse_rank": 0
    },
    {
      "rank": 91,
      "code": "600688",
      "name": "上海石化",
      "price": 3.49,
      "turnover": 10.07,
      "change_pct": 3.25,
      "hot_value": "435848.0",
      "rank_chg": 1,
      "popularity_tag": "3天2板",
      "concept_tags": [
        "航运概念",
        "氢能源"
      ],
      "analyse": "",
      "xueqiu_rank": 0,
      "browse_rank": 0
    },
    {
      "rank": 92,
      "code": "603618",
      "name": "杭电股份",
      "price": 41.71,
      "turnover": 13.53,
      "change_pct": -4.29,
      "hot_value": "433635.0",
      "rank_chg": -4,
      "popularity_tag": "",
      "concept_tags": [
        "光纤概念",
        "特高压"
      ],
      "analyse": "",
      "xueqiu_rank": 0,
      "browse_rank": 0
    },
    {
      "rank": 93,
      "code": "002484",
      "name": "江海股份",
      "price": 90.0,
      "turnover": 10.13,
      "change_pct": -6.59,
      "hot_value": "422486.0",
      "rank_chg": 2,
      "popularity_tag": "2天1板",
      "concept_tags": [
        "超级电容",
        "5G"
      ],
      "analyse": "",
      "xueqiu_rank": 0,
      "browse_rank": 0
    },
    {
      "rank": 94,
      "code": "603459",
      "name": "红板科技",
      "price": 98.48,
      "turnover": 24.25,
      "change_pct": -7.95,
      "hot_value": "421675.0",
      "rank_chg": 3,
      "popularity_tag": "",
      "concept_tags": [
        "共封装光学(CPO)",
        "PCB概念"
      ],
      "analyse": "",
      "xueqiu_rank": 0,
      "browse_rank": 0
    },
    {
      "rank": 95,
      "code": "002407",
      "name": "多氟多",
      "price": 33.2,
      "turnover": 11.73,
      "change_pct": 1.34,
      "hot_value": "420462.0",
      "rank_chg": -2,
      "popularity_tag": "",
      "concept_tags": [
        "氟化工概念",
        "PVDF概念"
      ],
      "analyse": "",
      "xueqiu_rank": 0,
      "browse_rank": 0
    },
    {
      "rank": 96,
      "code": "000657",
      "name": "中钨高新",
      "price": 70.1,
      "turnover": 5.66,
      "change_pct": -5.69,
      "hot_value": "418718.0",
      "rank_chg": 0,
      "popularity_tag": "",
      "concept_tags": [
        "小金属概念",
        "金属铜"
      ],
      "analyse": "",
      "xueqiu_rank": 0,
      "browse_rank": 0
    },
    {
      "rank": 97,
      "code": "600176",
      "name": "中国巨石",
      "price": 36.96,
      "turnover": 3.62,
      "change_pct": -3.72,
      "hot_value": "417423.0",
      "rank_chg": -3,
      "popularity_tag": "",
      "concept_tags": [
        "PCB概念",
        "2026一季报预增"
      ],
      "analyse": "",
      "xueqiu_rank": 0,
      "browse_rank": 0
    },
    {
      "rank": 98,
      "code": "002354",
      "name": "天娱数科",
      "price": 6.66,
      "turnover": 7.69,
      "change_pct": 10.08,
      "hot_value": "416704.0",
      "rank_chg": 3,
      "popularity_tag": "首板涨停",
      "concept_tags": [
        "小红书概念",
        "短剧游戏"
      ],
      "analyse": "行业原因：\n1、宇树科技于6月1日通过科创板IPO上会，国产人形机器人企业的资本化进程加速。\n2、英伟达近日发布NVIDIA Cosmos 3——面向物理AI的开放世界基础模型。黄仁勋表示，得益于多模态推理语言、视觉和世界模型领域的多项突破，物理AI爆发的时代已近在眼前。\n公司原因：\n1、据公司官微2025年7月21日消息，公司正在通过基于VLA的方案，积极加速物理AI技术的落地应用。公司致力于整合虚拟与物理智能系统，以推动人工智能在现实世界中的广泛应用。这一创新将有助于提升AI在各行业的适应能力，并促进相关技术的成熟与普及。\n2、据2026年4月21日年报，公司“高质量纹理3D铰接数据”等10项具身智能数据集已在北京国际大数据交易所完成资产登记，Behavision平台支持人形机器人等多类本体并亮相CES 2025。\n3、据2026年4月28日证券时报，公司与山西数据技术公司等合作，依托国家先进计算太原中心800PFlops AI算力打造公共算力服务平台，切入算力租赁赛道。\n4、据2026年4月21日年报，公司移动应用分发平台已上架DeepSeek、Kimi、文心一言等头部AI应用，长期为抖音、快手、小红书提供推广服务。\n\n（免责声明：本内容由AI技术搜集公开信息总结生成，仅供参考，不构成投资建议，以上市公司公告为准）",
      "xueqiu_rank": 0,
      "browse_rank": 0
    },
    {
      "rank": 99,
      "code": "002202",
      "name": "金风科技",
      "price": 23.0,
      "turnover": 3.46,
      "change_pct": -2.67,
      "hot_value": "414473.0",
      "rank_chg": 0,
      "popularity_tag": "",
      "concept_tags": [
        "商业航天",
        "柔性直流输电"
      ],
      "analyse": "",
      "xueqiu_rank": 0,
      "browse_rank": 0
    },
    {
      "rank": 100,
      "code": "002241",
      "name": "歌尔股份",
      "price": 24.82,
      "turnover": 6.34,
      "change_pct": -0.48,
      "hot_value": "412710.0",
      "rank_chg": -2,
      "popularity_tag": "",
      "concept_tags": [
        "同花顺果指数",
        "智能音箱"
      ],
      "analyse": "",
      "xueqiu_rank": 0,
      "browse_rank": 0
    }
  ]
}