{
  "update_time": "2026-06-23 04:09:34",
  "source": "同花顺热榜",
  "data": {
    "重组蛋白": [],
    "阿兹海默": [],
    "CAR-T细胞疗法": [],
    "单抗概念": [],
    "减肥药": [],
    "CRO": [],
    "创新药": [],
    "维生素": [],
    "肝炎概念": [],
    "SPD概念": [],
    "氦气概念": [],
    "肝素概念": [],
    "免疫治疗": [],
    "辅助生殖": [],
    "流感": [],
    "病原体防治": [],
    "昨日打二板以上表现": [],
    "特色药": [],
    "独家药品": [],
    "全息技术": [],
    "幽门螺杆菌概念": [],
    "长寿药": [],
    "中药概念": [],
    "生物疫苗": [],
    "昨日连板_含一字": [],
    "昨日首板": [],
    "病毒防治": [],
    "精准诊断": [],
    "体外诊断概念": [],
    "工业气体": [],
    "化妆品概念": [],
    "昨日涨停_含一字": [],
    "精准医疗": [],
    "毛发医疗": [],
    "合成生物": [],
    "轮毂电机": [],
    "昨日涨停": [],
    "微盘股": [],
    "医美概念": [],
    "创新医疗服务": [],
    "EDR概念": [],
    "工业大麻": [],
    "人造肉": [],
    "基因测序": [],
    "AI制药（医疗）": [],
    "微盘精选": [],
    "猪肉概念": [],
    "举牌": [],
    "医药医疗风格": [],
    "婴童概念": [],
    "氨纶": [],
    "其他生物制品": [],
    "辅料": [],
    "原料药": [],
    "化学制药": [],
    "其他医疗服务": [],
    "其他化学原料": [],
    "医疗研发外包": [],
    "化学制剂": [],
    "生物制品": [],
    "分立器件": [],
    "炭黑": [],
    "生活用纸": [],
    "家纺": [],
    "医药生物": [],
    "个护用品": [],
    "水泥制品": [],
    "医疗服务": [],
    "其他数字媒体": [],
    "中药Ⅲ": [],
    "中药Ⅱ": [],
    "化妆品制造及其他": [],
    "印染": [],
    "运动服装": [],
    "动物保健Ⅲ": [],
    "动物保健Ⅱ": [],
    "卫浴制品": [],
    "物业管理": [
      {
        "code": "601162",
        "name": "天风证券",
        "hot_value": "1318943.0",
        "rank": 57
      }
    ],
    "国有大型银行Ⅲ": [],
    "医药流通": [],
    "洗护用品": [],
    "医疗耗材": [],
    "美容护理": [],
    "医药商业": [],
    "厨房电器": [],
    "化妆品": [],
    "通信线缆及配套": [],
    "纺织制造": [],
    "鞋帽及其他": [],
    "快递": [],
    "体外诊断": [],
    "棉纺": [],
    "仓储物流": [],
    "房地产服务": [],
    "疫苗": [
      {
        "code": "002141",
        "name": "贤丰控股",
        "hot_value": "1178266.0",
        "rank": 72
      }
    ],
    "医疗器械": [],
    "焦炭Ⅲ": [],
    "焦炭Ⅱ": [],
    "定制家居": [],
    "水产养殖": []
  }
}