{
  "update_time": "2026-07-22 04:25:22",
  "source": "同花顺飙升榜",
  "total": 13,
  "data": [
    {
      "rank": 1,
      "code": "301132",
      "name": "满坤科技",
      "rate": "30420.5",
      "change_pct": 2.42,
      "hot_rank_chg": 22,
      "popularity_tag": "",
      "concept_tags": [
        "PCB概念",
        "共封装光学(CPO)"
      ],
      "analyse": ""
    },
    {
      "rank": 2,
      "code": "600560",
      "name": "金自天正",
      "rate": "1337.5",
      "change_pct": -2.08,
      "hot_rank_chg": 843,
      "popularity_tag": "",
      "concept_tags": [
        "新型工业化",
        "工业互联网"
      ],
      "analyse": ""
    },
    {
      "rank": 3,
      "code": "603158",
      "name": "腾龙股份",
      "rate": "684.5",
      "change_pct": -0.11,
      "hot_rank_chg": 271,
      "popularity_tag": "",
      "concept_tags": [
        "无线充电",
        "智能座舱"
      ],
      "analyse": ""
    },
    {
      "rank": 4,
      "code": "603353",
      "name": "和顺石油",
      "rate": "368.5",
      "change_pct": 6.33,
      "hot_rank_chg": 93,
      "popularity_tag": "",
      "concept_tags": [
        "俄乌冲突概念",
        "存储芯片"
      ],
      "analyse": ""
    },
    {
      "rank": 5,
      "code": "002767",
      "name": "先锋电子",
      "rate": "347.5",
      "change_pct": -0.12,
      "hot_rank_chg": 326,
      "popularity_tag": "",
      "concept_tags": [
        "新型工业化",
        "水利"
      ],
      "analyse": ""
    },
    {
      "rank": 6,
      "code": "301172",
      "name": "君逸数码",
      "rate": "137.5",
      "change_pct": 3.38,
      "hot_rank_chg": 138,
      "popularity_tag": "",
      "concept_tags": [
        "光纤概念",
        "共封装光学(CPO)"
      ],
      "analyse": ""
    },
    {
      "rank": 7,
      "code": "301528",
      "name": "多浦乐",
      "rate": "32.5",
      "change_pct": -1.13,
      "hot_rank_chg": 178,
      "popularity_tag": "",
      "concept_tags": [
        "专精特新",
        "成飞概念"
      ],
      "analyse": ""
    },
    {
      "rank": 8,
      "code": "688113",
      "name": "联测科技",
      "rate": "8.5",
      "change_pct": 4.01,
      "hot_rank_chg": 42,
      "popularity_tag": "",
      "concept_tags": [
        "专精特新",
        "比亚迪概念"
      ],
      "analyse": ""
    },
    {
      "rank": 9,
      "code": "300462",
      "name": "ST华铭",
      "rate": "7.5",
      "change_pct": -1.0,
      "hot_rank_chg": 42,
      "popularity_tag": "",
      "concept_tags": [
        "独角兽概念",
        "移动支付"
      ],
      "analyse": ""
    },
    {
      "rank": 10,
      "code": "688115",
      "name": "思林杰",
      "rate": "6.0",
      "change_pct": 0.48,
      "hot_rank_chg": 35,
      "popularity_tag": "",
      "concept_tags": [
        "芯片概念",
        "WiFi 6"
      ],
      "analyse": ""
    },
    {
      "rank": 11,
      "code": "920429",
      "name": "康比特",
      "rate": "5.0",
      "change_pct": 1.18,
      "hot_rank_chg": 30,
      "popularity_tag": "",
      "concept_tags": [
        "军民融合",
        "人工智能"
      ],
      "analyse": ""
    },
    {
      "rank": 12,
      "code": "603282",
      "name": "亚光股份",
      "rate": "3.0",
      "change_pct": -1.15,
      "hot_rank_chg": 50,
      "popularity_tag": "",
      "concept_tags": [
        "污水处理",
        "锂电池概念"
      ],
      "analyse": ""
    },
    {
      "rank": 13,
      "code": "920680",
      "name": "广道退",
      "rate": "1.5",
      "change_pct": 0,
      "hot_rank_chg": 5,
      "popularity_tag": "",
      "concept_tags": [],
      "analyse": ""
    }
  ]
}